MANIFEST.in
README.rst
setup.py
python_field/__init__.py
python_field/fields.py
python_field.egg-info/PKG-INFO
python_field.egg-info/SOURCES.txt
python_field.egg-info/dependency_links.txt
python_field.egg-info/pbr.json
python_field.egg-info/top_level.txt
python_field.egg-info/zip-safe
python_field/static/python_field/css/line-numbers.css
python_field/static/python_field/css/pythoncolors.css
python_field/static/python_field/js/codemirror.js
python_field/static/python_field/js/editor.js
python_field/static/python_field/js/highlight.js
python_field/static/python_field/js/mirrorframe.js
python_field/static/python_field/js/parsepython.js
python_field/static/python_field/js/python_field.js
python_field/static/python_field/js/select.js
python_field/static/python_field/js/stringstream.js
python_field/static/python_field/js/tokenize.js
python_field/static/python_field/js/undo.js
python_field/static/python_field/js/util.js